{"LIV0001":{"title":"La Perpétuelle croix","total":204,"types":{"person":[{"id":"person-000003","label":"Jésus-Christ","mentions":46},{"id":"person-000132","label":"Pilate","mentions":12},{"id":"person-000386","label":"Jesu Christe","mentions":11},{"id":"person-000429","label":"IrsvsCHRIST","mentions":10},{"id":"person-000129","label":"Jésus","mentions":9},{"id":"person-000135","label":"Marie","mentions":5},{"id":"person-000026","label":"S. Jean","mentions":4},{"id":"person-000445","label":"Simeon","mentions":4},{"id":"person-000654","label":"Anne","mentions":3},{"id":"person-000267","label":"Caiphe","mentions":3},{"id":"person-001472","label":"Mlerimnan Zlloyen","mentions":3},{"id":"person-000018","label":"saint Pierre","mentions":3},{"id":"person-001650","label":"Abram","mentions":2},{"id":"person-000264","label":"Anselme","mentions":2},{"id":"person-000324","label":"Chretien","mentions":2},{"id":"person-000089","label":"Daniel","mentions":2},{"id":"person-000007","label":"David","mentions":2},{"id":"person-001997","label":"DEVOTE","mentions":2},{"id":"person-002013","label":"DIUIN","mentions":2},{"id":"person-002034","label":"Eminentissime Cardinal Robert","mentions":2},{"id":"person-002252","label":"Jesvs","mentions":2},{"id":"person-002511","label":"Origée","mentions":2},{"id":"person-000485","label":"S. Marc","mentions":2},{"id":"person-000016","label":"Salomon","mentions":2},{"id":"person-002736","label":"Saulmais","mentions":2},{"id":"person-003095","label":"AMère de Dieu","mentions":1},{"id":"person-000001","label":"Augustin","mentions":1},{"id":"person-000029","label":"Bellarmin","mentions":1},{"id":"person-003533","label":"Caidhe","mentions":1},{"id":"person-000053","label":"César","mentions":1},{"id":"person-003654","label":"Cftr-e","mentions":1},{"id":"person-003707","label":"Christe","mentions":1},{"id":"person-004022","label":"Darlé","mentions":1},{"id":"person-000002","label":"Dieu","mentions":1},{"id":"person-004388","label":"Florentin Lambert","mentions":1},{"id":"person-000587","label":"Gerson","mentions":1},{"id":"person-004700","label":"Hermen Htleyen","mentions":1},{"id":"person-004719","label":"HeupRuse","mentions":1},{"id":"person-004827","label":"Igfus","mentions":1},{"id":"person-004833","label":"Iisvs","mentions":1},{"id":"person-000596","label":"Isaac","mentions":1},{"id":"person-000126","label":"Jacob","mentions":1},{"id":"person-004931","label":"Jcoma","mentions":1},{"id":"person-004986","label":"JeORAISON","mentions":1},{"id":"person-000074","label":"Jérémie","mentions":1},{"id":"person-000102","label":"Joab","mentions":1},{"id":"person-000039","label":"Joseph","mentions":1},{"id":"person-005015","label":"Josias","mentions":1},{"id":"person-000216","label":"Judas","mentions":1},{"id":"person-002280","label":"la Vierge","mentions":1},{"id":"person-000600","label":"Larron","mentions":1},{"id":"person-005294","label":"Léonard Léfsius","mentions":1},{"id":"person-005427","label":"MARIE DE BEAUVILLIERS","mentions":1},{"id":"person-005499","label":"Mcemnan Jlagén","mentions":1},{"id":"person-000013","label":"Moïse","mentions":1},{"id":"person-005735","label":"OLIVIER RICHÉCOEUR","mentions":1},{"id":"person-006018","label":"PoitIine","mentions":1},{"id":"person-000032","label":"S. Bernard","mentions":1},{"id":"person-000073","label":"S. Hérôme","mentions":1},{"id":"person-000075","label":"Saint Bonaventure","mentions":1},{"id":"person-001600","label":"Sunamite","mentions":1}],"place":[{"id":"place-000031","label":"Égypte","mentions":6},{"id":"place-000107","label":"monde","mentions":2},{"id":"place-000004","label":"Paris","mentions":2},{"id":"place-000701","label":"St Luc à","mentions":2},{"id":"place-001965","label":"ÀBBESSE","mentions":1},{"id":"place-000097","label":"Bethléem","mentions":1},{"id":"place-000068","label":"Bourges","mentions":1},{"id":"place-000998","label":"Cedron","mentions":1},{"id":"place-001041","label":"Cloistres","mentions":1},{"id":"place-001481","label":"mt Odge","mentions":1},{"id":"place-000158","label":"Sion","mentions":1},{"id":"place-000061","label":"Temple","mentions":1}],"organization":[{"id":"org-000357","label":"Apôtresyrie éléison","mentions":1},{"id":"org-000404","label":"Chtiste éléison","mentions":1},{"id":"org-000413","label":"Compagnie de JEsvs","mentions":1}],"work":[{"id":"work-000076","label":"Conjouislance","mentions":2},{"id":"work-000015","label":"Cantiques","mentions":1}],"event":[{"id":"event-000229","label":"crucifiément","mentions":1},{"id":"event-000285","label":"La perpétuelle Croix","mentions":1}],"artwork":[],"material":[{"id":"material-000159","label":"fers","mentions":1}],"technique":[],"date":[]}},"LIV0010":{"title":"Itinerarium","total":329,"types":{"person":[{"id":"person-000432","label":"Lomenius","mentions":10},{"id":"person-000663","label":"Auaugurius","mentions":6},{"id":"person-001247","label":"Arioſtum","mentions":3},{"id":"person-001268","label":"Brienneus","mentions":3},{"id":"person-001294","label":"Chriſtina","mentions":3},{"id":"person-001814","label":"BRIENNÆ COMIIEM","mentions":2},{"id":"person-001828","label":"Camœna","mentions":2},{"id":"person-001848","label":"Catullus","mentions":2},{"id":"person-001859","label":"Chanuti","mentions":2},{"id":"person-002345","label":"LVD. HENR. LOMENIVM.","mentions":2},{"id":"person-002436","label":"Mestra Venétias","mentions":2},{"id":"person-002504","label":"Olomutium","mentions":2},{"id":"person-002667","label":"Regina Ludouica Maria Gonzaga","mentions":2},{"id":"person-003028","label":"Alemannus","mentions":1},{"id":"person-003292","label":"Auaugurius mair","mentions":1},{"id":"person-003382","label":"Batauis","mentions":1},{"id":"person-003409","label":"BENIAMINVS PRIOLVS.","mentions":1},{"id":"person-003490","label":"Bromio","mentions":1},{"id":"person-003910","label":"Cæſaris","mentions":1},{"id":"person-003595","label":"Cardinale Grimaldo","mentions":1},{"id":"person-003596","label":"Cardinali Mazarino","mentions":1},{"id":"person-000268","label":"Catilina","mentions":1},{"id":"person-003679","label":"Charleuoio","mentions":1},{"id":"person-003852","label":"COSSARTIVS S. I","mentions":1},{"id":"person-000163","label":"Crispus","mentions":1},{"id":"person-003896","label":"Cynthius","mentions":1},{"id":"person-004071","label":"DESCARTES","mentions":1},{"id":"person-004150","label":"Dordracum","mentions":1},{"id":"person-004226","label":"Electori Brandeburgico","mentions":1},{"id":"person-004299","label":"Eugenium","mentions":1},{"id":"person-004359","label":"Ferdinandi Romanorum Regis","mentions":1},{"id":"person-004404","label":"FRANCISCVS OGERIVS.","mentions":1},{"id":"person-004423","label":"Friderico III. Imp","mentions":1},{"id":"person-004456","label":"GABRIEL COSSARTIVS","mentions":1},{"id":"person-004514","label":"Germani Epiſcopi","mentions":1},{"id":"person-004550","label":"Gonzaga","mentions":1},{"id":"person-004579","label":"Groeningenſis","mentions":1},{"id":"person-004609","label":"Guillelmi Arauſionenſium Principis","mentions":1},{"id":"person-004613","label":"Guſtauus Magnus","mentions":1},{"id":"person-004682","label":"Henricus Rantzouius","mentions":1},{"id":"person-004696","label":"Herletus","mentions":1},{"id":"person-004715","label":"Herus","mentions":1},{"id":"person-004718","label":"Hetroſca","mentions":1},{"id":"person-004823","label":"IATOR","mentions":1},{"id":"person-004842","label":"Illuſtrißime Brienne","mentions":1},{"id":"person-004852","label":"IMP","mentions":1},{"id":"person-004861","label":"Ioannem Philippum","mentions":1},{"id":"person-005116","label":"larius Oxenſtiernus","mentions":1},{"id":"person-005193","label":"Lioneus","mentions":1},{"id":"person-001422","label":"Liuius","mentions":1},{"id":"person-005251","label":"Luca","mentions":1},{"id":"person-002344","label":"Ludouicus","mentions":1},{"id":"person-005274","label":"LVDOVICI HENRICI","mentions":1},{"id":"person-005376","label":"Magontiaci Electoris","mentions":1},{"id":"person-005377","label":"Magontinum","mentions":1},{"id":"person-000538","label":"Maxime","mentions":1},{"id":"person-005517","label":"Mentelius","mentions":1},{"id":"person-005683","label":"Neronis","mentions":1},{"id":"person-005715","label":"Nouiomagum","mentions":1},{"id":"person-005953","label":"Piaſerius","mentions":1},{"id":"person-005960","label":"Pierideſque","mentions":1},{"id":"person-006048","label":"Popielus Rex","mentions":1},{"id":"person-006298","label":"Roterodamum","mentions":1},{"id":"person-006342","label":"S. Lucas","mentions":1},{"id":"person-006533","label":"SIGISMVNDVS","mentions":1},{"id":"person-006627","label":"Suſanus comes","mentions":1},{"id":"person-006858","label":"V DantZik","mentions":1},{"id":"person-006871","label":"Valentinianus","mentions":1},{"id":"person-006901","label":"VIATOR","mentions":1},{"id":"person-006919","label":"VLADISLAVS.","mentions":1},{"id":"person-006935","label":"Vua Fiaſconia","mentions":1},{"id":"person-007091","label":"Carolus Carolus Gustauus","mentions":0},{"id":"person-007210","label":"Gustauus Hornius","mentions":0}],"place":[{"id":"place-000035","label":"Romæ","mentions":9},{"id":"place-000156","label":"Poloniæ","mentions":6},{"id":"place-000177","label":"Brienneum","mentions":5},{"id":"place-000023","label":"Gallia","mentions":4},{"id":"place-000247","label":"Germania","mentions":4},{"id":"place-000252","label":"Ienicopiam","mentions":4},{"id":"place-000264","label":"Monti Briſiaco","mentions":4},{"id":"place-000275","label":"Riga","mentions":4},{"id":"place-000291","label":"Amiſiam","mentions":3},{"id":"place-000372","label":"Ratiſponam","mentions":3},{"id":"place-000396","label":"Varſauiæque","mentions":3},{"id":"place-000398","label":"Viſtula","mentions":3},{"id":"place-000399","label":"Vpſaliam","mentions":3},{"id":"place-000411","label":"Alſatia","mentions":2},{"id":"place-000416","label":"Amſtelodamum","mentions":2},{"id":"place-000444","label":"Boruſſiæ","mentions":2},{"id":"place-000445","label":"BOTNIA Occidentalis","mentions":2},{"id":"place-000480","label":"Comora","mentions":2},{"id":"place-000508","label":"Elbingam","mentions":2},{"id":"place-000516","label":"Flenſburgum","mentions":2},{"id":"place-000526","label":"GOTTORPIVM","mentions":2},{"id":"place-000532","label":"Hamburgum","mentions":2},{"id":"place-000567","label":"Liuoniam","mentions":2},{"id":"place-000572","label":"Lutetia Pariſiorum","mentions":2},{"id":"place-000580","label":"Mantua","mentions":2},{"id":"place-000605","label":"Montibelſigardo","mentions":2},{"id":"place-000624","label":"Oppenhemio","mentions":2},{"id":"place-000635","label":"Pernauiam","mentions":2},{"id":"place-000645","label":"Piſtoia","mentions":2},{"id":"place-000655","label":"Poſonij","mentions":2},{"id":"place-000667","label":"Reualiam","mentions":2},{"id":"place-000727","label":"VERONA","mentions":2},{"id":"place-000736","label":"Vuladiſlauia","mentions":2},{"id":"place-000757","label":"Abo","mentions":1},{"id":"place-000809","label":"Amſterdan","mentions":1},{"id":"place-000822","label":"Apennini","mentions":1},{"id":"place-000833","label":"Aremepncopain","mentions":1},{"id":"place-000871","label":"Aſchaffenburgum","mentions":1},{"id":"place-000858","label":"Auguſtam Vindelicorum","mentions":1},{"id":"place-000868","label":"Auſtriæ","mentions":1},{"id":"place-000890","label":"Batauorum","mentions":1},{"id":"place-000916","label":"Blonicoque","mentions":1},{"id":"place-000921","label":"BOMMELIA","mentions":1},{"id":"place-000923","label":"BONONIA","mentions":1},{"id":"place-000925","label":"Borgum Nylandiæ oppidum","mentions":1},{"id":"place-000926","label":"BORGVS","mentions":1},{"id":"place-000927","label":"BORM","mentions":1},{"id":"place-000934","label":"Brauuembergam","mentions":1},{"id":"place-000945","label":"Caffam","mentions":1},{"id":"place-000101","label":"Candie","mentions":1},{"id":"place-000974","label":"Careliæ","mentions":1},{"id":"place-000996","label":"Caſtro Gottorpij","mentions":1},{"id":"place-001016","label":"Cheſtochovva","mentions":1},{"id":"place-001039","label":"CLAVSA","mentions":1},{"id":"place-001046","label":"Codani ſinus","mentions":1},{"id":"place-001047","label":"COELO","mentions":1},{"id":"place-001052","label":"COLMENSEC","mentions":1},{"id":"place-001066","label":"Copenhaguen","mentions":1},{"id":"place-001076","label":"Cracouia","mentions":1},{"id":"place-001080","label":"Cruſchuram","mentions":1},{"id":"place-001081","label":"Cruſuicia","mentions":1},{"id":"place-001084","label":"Cuprimontium","mentions":1},{"id":"place-001085","label":"Curlandiam","mentions":1},{"id":"place-001096","label":"Danubium","mentions":1},{"id":"place-001099","label":"Delfſilio","mentions":1},{"id":"place-000500","label":"Delphos","mentions":1},{"id":"place-001121","label":"Dublino","mentions":1},{"id":"place-001141","label":"Ezuram","mentions":1},{"id":"place-001146","label":"Ferraria","mentions":1},{"id":"place-001148","label":"Finningiam","mentions":1},{"id":"place-001149","label":"FINNONIA","mentions":1},{"id":"place-001151","label":"Florentiæ","mentions":1},{"id":"place-001165","label":"Francofurtum","mentions":1},{"id":"place-001169","label":"Gabinio","mentions":1},{"id":"place-000522","label":"GENVA","mentions":1},{"id":"place-001187","label":"Gluſtadium","mentions":1},{"id":"place-001198","label":"Graudenſio","mentions":1},{"id":"place-001200","label":"GRONINGA","mentions":1},{"id":"place-001218","label":"Herbipolim Franconiæ","mentions":1},{"id":"place-001220","label":"Hernoſandia","mentions":1},{"id":"place-001227","label":"Holmiam","mentions":1},{"id":"place-001253","label":"Indiæ","mentions":1},{"id":"place-001255","label":"Ingriam","mentions":1},{"id":"place-001267","label":"Iſaram","mentions":1},{"id":"place-001329","label":"LAVRETVM","mentions":1},{"id":"place-001354","label":"Liburnum","mentions":1},{"id":"place-001382","label":"LVBECA","mentions":1},{"id":"place-001397","label":"Magontinum","mentions":1},{"id":"place-001398","label":"MAGVNTIACVM","mentions":1},{"id":"place-001426","label":"Mekelburgum","mentions":1},{"id":"place-001427","label":"Melerum lacum","mentions":1},{"id":"place-001429","label":"Memelium","mentions":1},{"id":"place-001430","label":"MEMELIVM","mentions":1},{"id":"place-001435","label":"Millakulam","mentions":1},{"id":"place-001439","label":"Mitauuiana arce","mentions":1},{"id":"place-001445","label":"MODESTIA","mentions":1},{"id":"place-001497","label":"Mœnum","mentions":1},{"id":"place-001498","label":"Mœnum in Franconia","mentions":1},{"id":"place-001449","label":"MONACHIVM","mentions":1},{"id":"place-001465","label":"MONS BELLIGARDVS","mentions":1},{"id":"place-001473","label":"Monte Fiaſcone","mentions":1},{"id":"place-001484","label":"Munich","mentions":1},{"id":"place-001486","label":"Muntpelgard","mentions":1},{"id":"place-001509","label":"Nemetum","mentions":1},{"id":"place-001518","label":"Niumeghen","mentions":1},{"id":"place-001521","label":"Norimberga","mentions":1},{"id":"place-001524","label":"Nouiomago Nemetum","mentions":1},{"id":"place-000621","label":"Nuremberg","mentions":1},{"id":"place-001527","label":"Oberbartauia","mentions":1},{"id":"place-001531","label":"Oldenburgum","mentions":1},{"id":"place-001548","label":"Ouer Iſſel","mentions":1},{"id":"place-001564","label":"PANNONIA","mentions":1},{"id":"place-001568","label":"PARISII","mentions":1},{"id":"place-001608","label":"Piſas","mentions":1},{"id":"place-001618","label":"Ploena","mentions":1},{"id":"place-001620","label":"Polangen","mentions":1},{"id":"place-001621","label":"Polonga Samogitiæ","mentions":1},{"id":"place-001628","label":"Pontificiam","mentions":1},{"id":"place-001644","label":"PRAGA","mentions":1},{"id":"place-001645","label":"Presbourg","mentions":1},{"id":"place-001670","label":"RAVA","mentions":1},{"id":"place-001741","label":"Salam flumen","mentions":1},{"id":"place-001766","label":"SCRACHICOVVIA","mentions":1},{"id":"place-001767","label":"Scrachiſchouia","mentions":1},{"id":"place-001779","label":"Sequanos","mentions":1},{"id":"place-001788","label":"Shertogenberg","mentions":1},{"id":"place-001792","label":"Sileſiam","mentions":1},{"id":"place-001800","label":"Smnalaiidia","mentions":1},{"id":"place-001808","label":"Stockholm","mentions":1},{"id":"place-000021","label":"Strasbourg","mentions":1},{"id":"place-001810","label":"Sudermaniæ","mentions":1},{"id":"place-001851","label":"Theut Naruam","mentions":1},{"id":"place-001877","label":"Torunio","mentions":1},{"id":"place-001914","label":"Valtigouia","mentions":1},{"id":"place-001919","label":"VENETIÆ","mentions":1},{"id":"place-001924","label":"VESONTIO","mentions":1},{"id":"place-001928","label":"Vetteri lacus","mentions":1},{"id":"place-001930","label":"Viburgo","mentions":1},{"id":"place-001931","label":"VICENTIA","mentions":1},{"id":"place-001932","label":"VIELISCA","mentions":1},{"id":"place-001933","label":"Vieliſcæ","mentions":1},{"id":"place-001940","label":"VINDOBONA","mentions":1},{"id":"place-001941","label":"Vindobonam","mentions":1},{"id":"place-001945","label":"Vmæ","mentions":1},{"id":"place-001946","label":"Vormacia","mentions":1},{"id":"place-001949","label":"Vrbs","mentions":1},{"id":"place-001954","label":"Vvien","mentions":1},{"id":"place-001963","label":"Zeeland","mentions":1},{"id":"place-001998","label":"Bieneburgus","mentions":0},{"id":"place-002048","label":"Medelpadia","mentions":0},{"id":"place-002052","label":"Morauia","mentions":0}],"organization":[],"work":[{"id":"work-000150","label":"ACTIS ET EPISTOLIS","mentions":1},{"id":"work-000169","label":"CARMEN.","mentions":1}],"event":[{"id":"event-000042","label":"bello","mentions":3},{"id":"event-000194","label":"bellum Germanicum","mentions":1},{"id":"event-000212","label":"Comitia","mentions":1},{"id":"event-000320","label":"Paſcua","mentions":1}],"artwork":[],"material":[{"id":"material-000119","label":"argento","mentions":1},{"id":"material-000122","label":"auro","mentions":1},{"id":"material-000158","label":"FERRO","mentions":1},{"id":"material-000042","label":"marmore","mentions":1}],"technique":[],"date":[{"id":"date-000053","label":"ANNO DOMINI CIO IOCXXXII","mentions":1},{"id":"date-000088","label":"Id. Octobris","mentions":1},{"id":"date-000096","label":"Kal. Aug.","mentions":1},{"id":"date-000097","label":"Kal. Iun","mentions":1},{"id":"date-000098","label":"Kal. Septembr","mentions":1},{"id":"date-000107","label":"M. CCCC. L.","mentions":1},{"id":"date-000108","label":"M. DC. LIV","mentions":1},{"id":"date-000109","label":"MARS","mentions":1}]}},"LIV0017":{"title":"Dialogue des causes de la corruption de l'éloquence","total":254,"types":{"person":[{"id":"person-000022","label":"Ciceron","mentions":28},{"id":"person-000356","label":"Maténus","mentions":12},{"id":"person-000507","label":"Asinius","mentions":8},{"id":"person-000240","label":"Brutus","mentions":7},{"id":"person-000610","label":"Messalla","mentions":7},{"id":"person-000669","label":"Caluus","mentions":6},{"id":"person-000757","label":"Saleius Bassus","mentions":6},{"id":"person-000059","label":"Caton","mentions":5},{"id":"person-000030","label":"Demôthène","mentions":5},{"id":"person-000053","label":"César","mentions":4},{"id":"person-000098","label":"Crassus","mentions":4},{"id":"person-000531","label":"Jules César","mentions":4},{"id":"person-000104","label":"Tacite","mentions":4},{"id":"person-001302","label":"Corninus","mentions":3},{"id":"person-000009","label":"Platon","mentions":3},{"id":"person-001719","label":"Aper","mentions":2},{"id":"person-001245","label":"Archias","mentions":2},{"id":"person-001252","label":"Aurelia","mentions":2},{"id":"person-000802","label":"Caius","mentions":2},{"id":"person-001842","label":"Carpuisque","mentions":2},{"id":"person-000819","label":"César Auguste","mentions":2},{"id":"person-001861","label":"Charles chappellain","mentions":2},{"id":"person-000163","label":"Crispus","mentions":2},{"id":"person-002000","label":"Diatogue","mentions":2},{"id":"person-001349","label":"Gallion","mentions":2},{"id":"person-000070","label":"Horace","mentions":2},{"id":"person-001068","label":"Lacédémone","mentions":2},{"id":"person-000063","label":"Lysias","mentions":2},{"id":"person-000231","label":"Orphée","mentions":2},{"id":"person-002522","label":"Pacvuius","mentions":2},{"id":"person-002605","label":"Pompeus","mentions":2},{"id":"person-000116","label":"Quintilien","mentions":2},{"id":"person-002654","label":"Quintus Pédius","mentions":2},{"id":"person-002749","label":"Sergius Galba","mentions":2},{"id":"person-000340","label":"Tite","mentions":2},{"id":"person-000341","label":"Vespasian","mentions":2},{"id":"person-002963","label":"Africanus","mentions":1},{"id":"person-000565","label":"Agamemnon","mentions":1},{"id":"person-000011","label":"Alexandre","mentions":1},{"id":"person-003215","label":"Appollon","mentions":1},{"id":"person-003271","label":"Asiaticus","mentions":1},{"id":"person-003296","label":"Aufidius Bassus","mentions":1},{"id":"person-001254","label":"Ausfi","mentions":1},{"id":"person-003516","label":"C. Carbo","mentions":1},{"id":"person-003537","label":"Caius Graccus","mentions":1},{"id":"person-003538","label":"Caius Lélius","mentions":1},{"id":"person-000145","label":"Caligula","mentions":1},{"id":"person-003572","label":"Canutius","mentions":1},{"id":"person-001280","label":"Cassius Severus","mentions":1},{"id":"person-003628","label":"Caton le vieil","mentions":1},{"id":"person-001957","label":"Cœlius","mentions":1},{"id":"person-003815","label":"Comédien","mentions":1},{"id":"person-001008","label":"Cornélia","mentions":1},{"id":"person-003879","label":"Crispus Vibius","mentions":1},{"id":"person-003891","label":"Curiatius Maternus","mentions":1},{"id":"person-004098","label":"Diodore le Stoique","mentions":1},{"id":"person-001025","label":"Dolabella","mentions":1},{"id":"person-004138","label":"Domitius Aper","mentions":1},{"id":"person-007017","label":"Éphère","mentions":1},{"id":"person-004265","label":"Eprius Marcellus","mentions":1},{"id":"person-004442","label":"Furnius","mentions":1},{"id":"person-004541","label":"Gnéius Pompeus","mentions":1},{"id":"person-004542","label":"Gnéus","mentions":1},{"id":"person-004981","label":"Jeavrie ba yrees anjère véterth","mentions":1},{"id":"person-005046","label":"Julius Secundus","mentions":1},{"id":"person-005072","label":"Jûte Fabius","mentions":1},{"id":"person-005075","label":"L. Bestia","mentions":1},{"id":"person-005105","label":"Lanature","mentions":1},{"id":"person-002310","label":"Lentulus","mentions":1},{"id":"person-001073","label":"Lipse","mentions":1},{"id":"person-002337","label":"Lucain","mentions":1},{"id":"person-000474","label":"Lucilius","mentions":1},{"id":"person-002341","label":"Lucius Crassus","mentions":1},{"id":"person-000721","label":"Marcellus","mentions":1},{"id":"person-005408","label":"Marcellus Eprius","mentions":1},{"id":"person-001099","label":"Mecenas","mentions":1},{"id":"person-001459","label":"Menenius Agrippa","mentions":1},{"id":"person-005659","label":"Métrodorus","mentions":1},{"id":"person-005776","label":"P. Quintius","mentions":1},{"id":"person-000014","label":"Philippe","mentions":1},{"id":"person-006508","label":"Servilius Nouianus","mentions":1},{"id":"person-006554","label":"Sisenna","mentions":1},{"id":"person-000306","label":"Sophocle","mentions":1},{"id":"person-006660","label":"T. Milo","mentions":1},{"id":"person-006883","label":"Varius","mentions":1},{"id":"person-000368","label":"Varron","mentions":1},{"id":"person-006905","label":"Vigenere","mentions":1},{"id":"person-006913","label":"Vipsanius Messalla","mentions":1},{"id":"person-000252","label":"Virgile","mentions":1},{"id":"person-007112","label":"Cécina","mentions":0},{"id":"person-002131","label":"Gracchus","mentions":0}],"place":[{"id":"place-000001","label":"Rome","mentions":2},{"id":"place-000971","label":"Capoue","mentions":1},{"id":"place-000336","label":"Gaules","mentions":1},{"id":"place-001433","label":"Messal","mentions":1},{"id":"place-000017","label":"Palais","mentions":1},{"id":"place-000004","label":"Paris","mentions":1},{"id":"place-001763","label":"Saïs","mentions":1},{"id":"place-001888","label":"Tribunat","mentions":1},{"id":"place-001923","label":"Verceil","mentions":1}],"organization":[{"id":"org-000009","label":"Sénat","mentions":8},{"id":"org-000057","label":"Stoiciens","mentions":2},{"id":"org-000130","label":"Academies","mentions":1},{"id":"org-000369","label":"avocats","mentions":1},{"id":"org-000421","label":"CoNRART","mentions":1},{"id":"org-000674","label":"éoliers","mentions":1},{"id":"org-000116","label":"Peripateticiens","mentions":1},{"id":"org-000172","label":"Rhéteurs","mentions":1}],"work":[{"id":"work-000082","label":"Dialéctique","mentions":2},{"id":"work-000080","label":"Dialogue","mentions":2},{"id":"work-000175","label":"composition","mentions":1},{"id":"work-000004","label":"Grammaire","mentions":1},{"id":"work-000013","label":"Poésie","mentions":1},{"id":"work-000022","label":"vers","mentions":1}],"event":[{"id":"event-000008","label":"siècle","mentions":4},{"id":"event-000197","label":"brigandages","mentions":1},{"id":"event-000125","label":"guerres","mentions":1},{"id":"event-000302","label":"matière divine","mentions":1},{"id":"event-000081","label":"siècles passés","mentions":1},{"id":"event-000356","label":"Tous les siècles","mentions":1},{"id":"event-000357","label":"tradidie","mentions":1},{"id":"event-000358","label":"tradidieDomitius","mentions":1},{"id":"event-000161","label":"Tragédie","mentions":1}],"artwork":[],"material":[{"id":"material-000001","label":"matière","mentions":3},{"id":"material-000002","label":"marbre","mentions":1}],"technique":[{"id":"technique-000042","label":"composition","mentions":1},{"id":"technique-000001","label":"style","mentions":1}],"date":[{"id":"date-000129","label":"sixieme année","mentions":1}]}},"LIV0019":{"title":"Lettres touchant... la langue françoise","total":111,"types":{"person":[{"id":"person-000673","label":"Ccécéron","mentions":6},{"id":"person-000374","label":"Arondelle","mentions":5},{"id":"person-000049","label":"Malherbe","mentions":5},{"id":"person-000721","label":"Marcellus","mentions":5},{"id":"person-000020","label":"Plutarque","mentions":4},{"id":"person-001474","label":"Monseigneur l’Eminentisime Cardinal","mentions":3},{"id":"person-000001","label":"Augustin","mentions":2},{"id":"person-002359","label":"M ONSIEUR","mentions":2},{"id":"person-002424","label":"Melantho","mentions":2},{"id":"person-000119","label":"Philosophe","mentions":2},{"id":"person-002955","label":"Aduocat","mentions":1},{"id":"person-000313","label":"Alexandre le Grand","mentions":1},{"id":"person-000153","label":"Apollon","mentions":1},{"id":"person-003575","label":"Capitaine Corfinius","mentions":1},{"id":"person-000268","label":"Catilina","mentions":1},{"id":"person-003674","label":"Charles le Sage","mentions":1},{"id":"person-000105","label":"Charles-Quint","mentions":1},{"id":"person-000162","label":"Clement Alexandrin","mentions":1},{"id":"person-002878","label":"Écrivain","mentions":1},{"id":"person-000836","label":"Florus","mentions":1},{"id":"person-001350","label":"Gallus Asinius","mentions":1},{"id":"person-000699","label":"Germanicus","mentions":1},{"id":"person-004678","label":"Henri quatriesme","mentions":1},{"id":"person-000295","label":"Hesiode","mentions":1},{"id":"person-000197","label":"Jacques","mentions":1},{"id":"person-002294","label":"Largius Licinius","mentions":1},{"id":"person-001439","label":"Macrobe","mentions":1},{"id":"person-000013","label":"Moïse","mentions":1},{"id":"person-005686","label":"Niailierbe","mentions":1},{"id":"person-005692","label":"Nicolas de la Côte","mentions":1},{"id":"person-000009","label":"Platon","mentions":1},{"id":"person-006038","label":"Pomponius","mentions":1},{"id":"person-006109","label":"Préste-Ian","mentions":1},{"id":"person-000116","label":"Quintilien","mentions":1},{"id":"person-000026","label":"S. Jean","mentions":1},{"id":"person-000018","label":"saint Pierre","mentions":1},{"id":"person-000758","label":"Saluste","mentions":1},{"id":"person-000021","label":"Sénèque","mentions":1},{"id":"person-006662","label":"Tacite Français","mentions":1},{"id":"person-000339","label":"Théocrite","mentions":1},{"id":"person-006729","label":"Thomas non","mentions":1},{"id":"person-000252","label":"Virgile","mentions":1},{"id":"person-006924","label":"Votre Majesté Sire","mentions":1},{"id":"person-000137","label":"Zénon","mentions":1}],"place":[{"id":"place-001020","label":"Chypre","mentions":1},{"id":"place-001067","label":"Corfinium","mentions":1},{"id":"place-000004","label":"Paris","mentions":1},{"id":"place-000001","label":"Rome","mentions":1},{"id":"place-000375","label":"Savoie","mentions":1},{"id":"place-000030","label":"ville","mentions":1}],"organization":[{"id":"org-000041","label":"Compagnie","mentions":1},{"id":"org-000542","label":"Matelots","mentions":1}],"work":[{"id":"work-000044","label":"Remarques","mentions":4},{"id":"work-000004","label":"Grammaire","mentions":2},{"id":"work-000037","label":"Homère","mentions":2},{"id":"work-000095","label":"Hyperboles","mentions":2},{"id":"work-000132","label":"Préface","mentions":2},{"id":"work-000203","label":"Décalogue","mentions":1},{"id":"work-000227","label":"Je Ciel","mentions":1},{"id":"work-000236","label":"Lettre","mentions":1},{"id":"work-000013","label":"Poésie","mentions":1},{"id":"work-000283","label":"Poésie Hébraïque","mentions":1},{"id":"work-000128","label":"Politique","mentions":1},{"id":"work-000289","label":"Pseaumes","mentions":1},{"id":"work-000304","label":"Tapisseries","mentions":1},{"id":"work-000307","label":"Thehonnêtes","mentions":1}],"event":[{"id":"event-000081","label":"siècles passés","mentions":1}],"artwork":[{"id":"artwork-000014","label":"ornement","mentions":2},{"id":"artwork-000053","label":"Thermopyles","mentions":1}],"material":[{"id":"material-000033","label":"sable","mentions":2},{"id":"material-000021","label":"chaux","mentions":1},{"id":"material-000011","label":"papier","mentions":1},{"id":"material-000067","label":"toile","mentions":1}],"technique":[{"id":"technique-000001","label":"style","mentions":3}],"date":[]}},"LIV0020":{"title":"Considérations sur l'éloquence françoise de ce tems","total":352,"types":{"person":[{"id":"person-000022","label":"Ciceron","mentions":28},{"id":"person-000030","label":"Demôthène","mentions":13},{"id":"person-000116","label":"Quintilien","mentions":12},{"id":"person-000024","label":"Socrate","mentions":12},{"id":"person-000009","label":"Platon","mentions":10},{"id":"person-000333","label":"Longinus","mentions":9},{"id":"person-000021","label":"Sénèque","mentions":6},{"id":"person-000025","label":"Aristote","mentions":5},{"id":"person-001201","label":"Théon","mentions":4},{"id":"person-001193","label":"Theopompe","mentions":4},{"id":"person-000556","label":"Thucidide","mentions":4},{"id":"person-001214","label":"Achille statius","mentions":3},{"id":"person-000969","label":"Apollonius","mentions":3},{"id":"person-000178","label":"Gorgias","mentions":3},{"id":"person-001099","label":"Mecenas","mentions":3},{"id":"person-000730","label":"Ménandre","mentions":3},{"id":"person-000894","label":"Philemon","mentions":3},{"id":"person-001530","label":"Pollion","mentions":3},{"id":"person-000137","label":"Zénon","mentions":3},{"id":"person-001642","label":"A. Gellius","mentions":2},{"id":"person-000452","label":"Apulée","mentions":2},{"id":"person-000001","label":"Augustin","mentions":2},{"id":"person-001832","label":"Cardauus","mentions":2},{"id":"person-000515","label":"Chrysippe","mentions":2},{"id":"person-001881","label":"Ciest dili- Ceron","mentions":2},{"id":"person-002044","label":"Ennius","mentions":2},{"id":"person-002166","label":"Henry Étienne","mentions":2},{"id":"person-000156","label":"Homère","mentions":2},{"id":"person-000070","label":"Horace","mentions":2},{"id":"person-000602","label":"Lucien","mentions":2},{"id":"person-000474","label":"Lucilius","mentions":2},{"id":"person-001429","label":"Lycurgue","mentions":2},{"id":"person-000063","label":"Lysias","mentions":2},{"id":"person-001112","label":"Nicias","mentions":2},{"id":"person-001512","label":"Phauorin","mentions":2},{"id":"person-000027","label":"Pline","mentions":2},{"id":"person-001160","label":"Roscius","mentions":2},{"id":"person-002818","label":"Théophrae","mentions":2},{"id":"person-000308","label":"Tibère","mentions":2},{"id":"person-002862","label":"Vulcain","mentions":2},{"id":"person-002958","label":"Aetion","mentions":1},{"id":"person-000011","label":"Alexandre","mentions":1},{"id":"person-003037","label":"Alexandre le Sophiste","mentions":1},{"id":"person-001230","label":"Anacreon","mentions":1},{"id":"person-001705","label":"Anaxagore","mentions":1},{"id":"person-003229","label":"Archilocus","mentions":1},{"id":"person-001248","label":"Aristippe","mentions":1},{"id":"person-003261","label":"Arrian","mentions":1},{"id":"person-000192","label":"Auguste","mentions":1},{"id":"person-003340","label":"Bacchilides","mentions":1},{"id":"person-003358","label":"Baptiste Léon","mentions":1},{"id":"person-003541","label":"Calamides","mentions":1},{"id":"person-000145","label":"Caligula","mentions":1},{"id":"person-001278","label":"Carneades","mentions":1},{"id":"person-000059","label":"Caton","mentions":1},{"id":"person-003645","label":"Centons","mentions":1},{"id":"person-000053","label":"César","mentions":1},{"id":"person-003844","label":"Cornélius Celsus","mentions":1},{"id":"person-004049","label":"Demades","mentions":1},{"id":"person-004062","label":"Denis E. aa","mentions":1},{"id":"person-004081","label":"Dian","mentions":1},{"id":"person-000420","label":"Diodore","mentions":1},{"id":"person-004123","label":"Docteur Gratien","mentions":1},{"id":"person-004217","label":"ECEHÉMS","mentions":1},{"id":"person-006983","label":"Échines","mentions":1},{"id":"person-000311","label":"Épicure","mentions":1},{"id":"person-000141","label":"Euripide","mentions":1},{"id":"person-000697","label":"Galien","mentions":1},{"id":"person-001350","label":"Gallus Asinius","mentions":1},{"id":"person-004493","label":"Gauiais","mentions":1},{"id":"person-004553","label":"Gorgias Léontin","mentions":1},{"id":"person-004631","label":"Hadrien","mentions":1},{"id":"person-004632","label":"Hafs","mentions":1},{"id":"person-004640","label":"Halycarnasse","mentions":1},{"id":"person-001381","label":"Hécube","mentions":1},{"id":"person-004665","label":"Heliodore","mentions":1},{"id":"person-000146","label":"Hercule","mentions":1},{"id":"person-001373","label":"Hermogène","mentions":1},{"id":"person-004740","label":"Hippias Élien","mentions":1},{"id":"person-001378","label":"Hortensius","mentions":1},{"id":"person-004942","label":"Jean Baptiste Léon","mentions":1},{"id":"person-005065","label":"Jéononimus le Philosophe","mentions":1},{"id":"person-000431","label":"Laert","mentions":1},{"id":"person-000258","label":"Lucrece","mentions":1},{"id":"person-002373","label":"M. Pomponius Marcellus","mentions":1},{"id":"person-001091","label":"Marc Antonin","mentions":1},{"id":"person-001485","label":"Nicandre","mentions":1},{"id":"person-000260","label":"Pausanias","mentions":1},{"id":"person-005879","label":"Pepiie","mentions":1},{"id":"person-000198","label":"Pericles","mentions":1},{"id":"person-005883","label":"Perionius","mentions":1},{"id":"person-000747","label":"Pétrone","mentions":1},{"id":"person-005894","label":"Phal.","mentions":1},{"id":"person-000336","label":"Phidias","mentions":1},{"id":"person-005942","label":"Phrygien","mentions":1},{"id":"person-000284","label":"Pindare","mentions":1},{"id":"person-002595","label":"Pison","mentions":1},{"id":"person-000020","label":"Plutarque","mentions":1},{"id":"person-000111","label":"Poète","mentions":1},{"id":"person-006024","label":"Polilates","mentions":1},{"id":"person-000897","label":"Polybe","mentions":1},{"id":"person-001143","label":"Protogène","mentions":1},{"id":"person-006146","label":"Quat","mentions":1},{"id":"person-006155","label":"Quintilien Ciceron","mentions":1},{"id":"person-002725","label":"Salluste","mentions":1},{"id":"person-006472","label":"Scithe","mentions":1},{"id":"person-002786","label":"Sébastien Cramoisi","mentions":1},{"id":"person-006535","label":"Silesien","mentions":1},{"id":"person-000306","label":"Sophocle","mentions":1},{"id":"person-000554","label":"Strabon","mentions":1},{"id":"person-006614","label":"Suet","mentions":1},{"id":"person-006663","label":"Taison","mentions":1},{"id":"person-006845","label":"Térence","mentions":1},{"id":"person-000495","label":"Ulysse","mentions":1},{"id":"person-006890","label":"Vectius","mentions":1},{"id":"person-006898","label":"Verres","mentions":1},{"id":"person-000252","label":"Virgile","mentions":1},{"id":"person-002871","label":"Zeuxis","mentions":1},{"id":"person-007082","label":"bist","mentions":0},{"id":"person-007138","label":"deOras","mentions":0},{"id":"person-007144","label":"devitafua","mentions":0},{"id":"person-007186","label":"ExDion","mentions":0},{"id":"person-007214","label":"Halie","mentions":0},{"id":"person-007247","label":"Isoer","mentions":0},{"id":"person-007285","label":"Masear","mentions":0},{"id":"person-007340","label":"Phedrus","mentions":0}],"place":[{"id":"place-000001","label":"Rome","mentions":3},{"id":"place-000405","label":"Acacio","mentions":2},{"id":"place-000004","label":"Paris","mentions":2},{"id":"place-000641","label":"Phéniicie","mentions":2},{"id":"place-000425","label":"Athénies","mentions":1},{"id":"place-000432","label":"Barbarie","mentions":1},{"id":"place-001079","label":"Crotone","mentions":1},{"id":"place-001095","label":"Danube","mentions":1},{"id":"place-000336","label":"Gaules","mentions":1},{"id":"place-000085","label":"Macedoine","mentions":1},{"id":"place-000636","label":"Perse","mentions":1},{"id":"place-000019","label":"Sparte","mentions":1},{"id":"place-000159","label":"Syracuse","mentions":1},{"id":"place-002019","label":"ExDion","mentions":0},{"id":"place-002029","label":"Halic","mentions":0}],"organization":[{"id":"org-000015","label":"Jurisconsultes","mentions":2},{"id":"org-000116","label":"Peripateticiens","mentions":2},{"id":"org-000168","label":"Privilège du Roi","mentions":2},{"id":"org-000302","label":"Pythagoriens","mentions":2},{"id":"org-000024","label":"République","mentions":2},{"id":"org-000172","label":"Rhéteurs","mentions":2},{"id":"org-000341","label":"Academie des morts","mentions":1},{"id":"org-000359","label":"aragnées","mentions":1},{"id":"org-000201","label":"Architectes","mentions":1},{"id":"org-000050","label":"armée","mentions":1},{"id":"org-000453","label":"Démocraties","mentions":1},{"id":"org-000670","label":"Égyptiens","mentions":1},{"id":"org-000031","label":"Lacédémoniens","mentions":1},{"id":"org-000563","label":"Oratoire","mentions":1},{"id":"org-000621","label":"République des lettres","mentions":1},{"id":"org-000057","label":"Stoiciens","mentions":1}],"work":[{"id":"work-000003","label":"Rhétorique","mentions":11},{"id":"work-000004","label":"Grammaire","mentions":5},{"id":"work-000006","label":"Oraison","mentions":3},{"id":"work-000114","label":"Morale","mentions":2},{"id":"work-000137","label":"Topiques","mentions":2},{"id":"work-000158","label":"Argumentum","mentions":1},{"id":"work-000173","label":"Ciceromastix","mentions":1},{"id":"work-000204","label":"Démphène","mentions":1},{"id":"work-000083","label":"discours","mentions":1},{"id":"work-000063","label":"Éloquence","mentions":1},{"id":"work-000215","label":"Géographie","mentions":1},{"id":"work-000213","label":"Grammaire solœciâmes","mentions":1},{"id":"work-000229","label":"Jronies","mentions":1},{"id":"work-000123","label":"Philosophie","mentions":1},{"id":"work-000128","label":"Politique","mentions":1},{"id":"work-000134","label":"Rhétorique Française","mentions":1},{"id":"work-000010","label":"Romans","mentions":1},{"id":"work-000293","label":"Romulo","mentions":1},{"id":"work-000312","label":"Tragédies","mentions":1},{"id":"work-000314","label":"Tropes","mentions":1}],"event":[{"id":"event-000037","label":"Rencontre","mentions":3},{"id":"event-000090","label":"chute de Troie","mentions":1}],"artwork":[],"material":[{"id":"material-000001","label":"matière","mentions":3},{"id":"material-000041","label":"liège","mentions":2},{"id":"material-000132","label":"bonne matière","mentions":1},{"id":"material-000011","label":"papier","mentions":1}],"technique":[{"id":"technique-000001","label":"style","mentions":7},{"id":"technique-000039","label":"Astrologie","mentions":1},{"id":"technique-000027","label":"Phisionomie","mentions":1},{"id":"technique-000004","label":"prose","mentions":1}],"date":[{"id":"date-000027","label":"cents ans auparavant","mentions":2}]}}}